Workbook

Sheet Como usar
A1: Kit de Arranque · Controle de Estoque
A2: Resolvo Já · resolvoja.com
B4: Passo a passo
A5: 1 | B5: Na aba Produtos, cadastre cada item com um código único, o estoque que você tem hoje (Estoque inicial) e o Estoque mínimo, a quantidade abaixo da qual você precisa comprar de novo.
A6: 2 | B6: Toda vez que um produto entrar (compra, devolução) ou sair (venda, perda, uso interno), registre uma linha na aba Movimentações. Escolha o código na lista; o nome do produto aparece sozinho.
A7: 3 | B7: Na aba Produtos, o Saldo atual e a Situação são recalculados na hora: verde = OK, amarelo = repor, vermelho = sem estoque.
A8: 4 | B8: Use a coluna Sugestão de compra para montar o pedido ao fornecedor: ela indica quanto comprar para voltar ao dobro do estoque mínimo.
A9: 5 | B9: O Painel resume quantos itens precisam de reposição e quanto dinheiro está parado em estoque.
B11: Legenda das colunas
B12: Cabeçalho azul escuro: você preenche.
B13: Cabeçalho azul claro: calculado automaticamente, não precisa mexer.
B15: Dicas
B16: • Faça um inventário (contagem física) uma vez por mês. Se a contagem não bater com o Saldo atual, registre a diferença como Entrada ou Saída com a observação "ajuste de inventário".
B17: • Para definir o estoque mínimo: média vendida por dia × dias que o fornecedor leva para entregar, com uma folga.
B18: • Itens com muito valor parado e pouca saída são candidatos a promoção ou a comprar menos na próxima vez.
B20: Os dados que já vêm na planilha são exemplos para você ver tudo funcionando. Apague o conteúdo das linhas de exemplo (só as colunas de cabeçalho escuro) e comece a usar.

Sheet Painel
A1: Painel do Estoque
A2: Atualiza sozinho conforme você preenche as outras abas.
A4: Produtos cadastrados | B4: =COUNTA(Produtos!$A$5:$A$504)
A5: Itens para repor | B5: =COUNTIF(Produtos!$L$5:$L$504,"REPOR")
A6: Itens sem estoque | B6: =COUNTIF(Produtos!$L$5:$L$504,"SEM ESTOQUE")
A7: Valor total em estoque (custo) | B7: =SUM(Produtos!$M$5:$M$504)
A8: Unidades a comprar (sugestão) | B8: =SUM(Produtos!$N$5:$N$504)
A9: Movimentações nos últimos 30 dias | B9: =COUNTIFS('Movimentações'!$A$5:$A$5000,">="&(TODAY()-30))

Sheet Produtos
A1: Produtos
A2: Um produto por linha. O código precisa ser único.
A4: Código | B4: Produto | C4: Categoria | D4: Unidade | E4: Custo unitário | F4: Preço de venda | G4: Estoque inicial | H4: Estoque mínimo | I4: Entradas | J4: Saídas | K4: Saldo atual | L4: Situação | M4: Valor em estoque | N4: Sugestão de compra | O4: Margem
A5: P001 | B5: Café torrado 500 g | C5: Mercearia | D5: pct | E5: 14.9 | F5: 24.9 | G5: 40 | H5: 15 | I5: =IF(A5="","",SUMIFS('Movimentações'!$E$5:$E$5000,'Movimentações'!$B$5:$B$5000,A5,'Movimentações'!$D$5:$D$5000,"Entrada")) | J5: =IF(A5="","",SUMIFS('Movimentações'!$E$5:$E$5000,'Movimentações'!$B$5:$B$5000,A5,'Movimentações'!$D$5:$D$5000,"Saída")) | K5: =IF(A5="","",G5+I5-J5) | L5: =IF(A5="","",IF(K5<=0,"SEM ESTOQUE",IF(K5<=H5,"REPOR","OK"))) | M5: =IF(A5="","",MAX(K5,0)*E5) | N5: =IF(A5="","",IF(K5<=H5,MAX(2*H5-K5,0),0)) | O5: =IF(OR(A5="",F5=0,F5=""),"",(F5-E5)/F5)
A6: P002 | B6: Açúcar refinado 1 kg | C6: Mercearia | D6: pct | E6: 4.2 | F6: 6.99 | G6: 25 | H6: 20 | I6: =IF(A6="","",SUMIFS('Movimentações'!$E$5:$E$5000,'Movimentações'!$B$5:$B$5000,A6,'Movimentações'!$D$5:$D$5000,"Entrada")) | J6: =IF(A6="","",SUMIFS('Movimentações'!$E$5:$E$5000,'Movimentações'!$B$5:$B$5000,A6,'Movimentações'!$D$5:$D$5000,"Saída")) | K6: =IF(A6="","",G6+I6-J6) | L6: =IF(A6="","",IF(K6<=0,"SEM ESTOQUE",IF(K6<=H6,"REPOR","OK"))) | M6: =IF(A6="","",MAX(K6,0)*E6) | N6: =IF(A6="","",IF(K6<=H6,MAX(2*H6-K6,0),0)) | O6: =IF(OR(A6="",F6=0,F6=""),"",(F6-E6)/F6)
A7: P003 | B7: Leite integral 1 L | C7: Laticínios | D7: L | E7: 3.8 | F7: 5.99 | G7: 60 | H7: 30 | I7: =IF(A7="","",SUMIFS('Movimentações'!$E$5:$E$5000,'Movimentações'!$B$5:$B$5000,A7,'Movimentações'!$D$5:$D$5000,"Entrada")) | J7: =IF(A7="","",SUMIFS('Movimentações'!$E$5:$E$5000,'Movimentações'!$B$5:$B$5000,A7,'Movimentações'!$D$5:$D$5000,"Saída")) | K7: =IF(A7="","",G7+I7-J7) | L7: =IF(A7="","",IF(K7<=0,"SEM ESTOQUE",IF(K7<=H7,"REPOR","OK"))) | M7: =IF(A7="","",MAX(K7,0)*E7) | N7: =IF(A7="","",IF(K7<=H7,MAX(2*H7-K7,0),0)) | O7: =IF(OR(A7="",F7=0,F7=""),"",(F7-E7)/F7)
A8: P004 | B8: Copo descartável 200 ml | C8: Descartáveis | D8: pct | E8: 6.5 | F8: 11 | G8: 12 | H8: 10 | I8: =IF(A8="","",SUMIFS('Movimentações'!$E$5:$E$5000,'Movimentações'!$B$5:$B$5000,A8,'Movimentações'!$D$5:$D$5000,"Entrada")) | J8: =IF(A8="","",SUMIFS('Movimentações'!$E$5:$E$5000,'Movimentações'!$B$5:$B$5000,A8,'Movimentações'!$D$5:$D$5000,"Saída")) | K8: =IF(A8="","",G8+I8-J8) | L8: =IF(A8="","",IF(K8<=0,"SEM ESTOQUE",IF(K8<=H8,"REPOR","OK"))) | M8: =IF(A8="","",MAX(K8,0)*E8) | N8: =IF(A8="","",IF(K8<=H8,MAX(2*H8-K8,0),0)) | O8: =IF(OR(A8="",F8=0,F8=""),"",(F8-E8)/F8)
A9: P005 | B9: Guardanapo | C9: Descartáveis | D9: pct | E9: 2.1 | F9: 4.5 | G9: 30 | H9: 10 | I9: =IF(A9="","",SUMIFS('Movimentações'!$E$5:$E$5000,'Movimentações'!$B$5:$B$5000,A9,'Movimentações'!$D$5:$D$5000,"Entrada")) | J9: =IF(A9="","",SUMIFS('Movimentações'!$E$5:$E$5000,'Movimentações'!$B$5:$B$5000,A9,'Movimentações'!$D$5:$D$5000,"Saída")) | K9: =IF(A9="","",G9+I9-J9) | L9: =IF(A9="","",IF(K9<=0,"SEM ESTOQUE",IF(K9<=H9,"REPOR","OK"))) | M9: =IF(A9="","",MAX(K9,0)*E9) | N9: =IF(A9="","",IF(K9<=H9,MAX(2*H9-K9,0),0)) | O9: =IF(OR(A9="",F9=0,F9=""),"",(F9-E9)/F9)
A10: P006 | B10: Chocolate em pó 400 g | C10: Mercearia | D10: un | E10: 9.8 | F10: 16.9 | G10: 8 | H10: 6 | I10: =IF(A10="","",SUMIFS('Movimentações'!$E$5:$E$5000,'Movimentações'!$B$5:$B$5000,A10,'Movimentações'!$D$5:$D$5000,"Entrada")) | J10: =IF(A10="","",SUMIFS('Movimentações'!$E$5:$E$5000,'Movimentações'!$B$5:$B$5000,A10,'Movimentações'!$D$5:$D$5000,"Saída")) | K10: =IF(A10="","",G10+I10-J10) | L10: =IF(A10="","",IF(K10<=0,"SEM ESTOQUE",IF(K10<=H10,"REPOR","OK"))) | M10: =IF(A10="","",MAX(K10,0)*E10) | N10: =IF(A10="","",IF(K10<=H10,MAX(2*H10-K10,0),0)) | O10: =IF(OR(A10="",F10=0,F10=""),"",(F10-E10)/F10)
A11: P007 | B11: Filtro de papel 103 | C11: Mercearia | D11: cx | E11: 3.9 | F11: 7.5 | G11: 18 | H11: 8 | I11: =IF(A11="","",SUMIFS('Movimentações'!$E$5:$E$5000,'Movimentações'!$B$5:$B$5000,A11,'Movimentações'!$D$5:$D$5000,"Entrada")) | J11: =IF(A11="","",SUMIFS('Movimentações'!$E$5:$E$5000,'Movimentações'!$B$5:$B$5000,A11,'Movimentações'!$D$5:$D$5000,"Saída")) | K11: =IF(A11="","",G11+I11-J11) | L11: =IF(A11="","",IF(K11<=0,"SEM ESTOQUE",IF(K11<=H11,"REPOR","OK"))) | M11: =IF(A11="","",MAX(K11,0)*E11) | N11: =IF(A11="","",IF(K11<=H11,MAX(2*H11-K11,0),0)) | O11: =IF(OR(A11="",F11=0,F11=""),"",(F11-E11)/F11)
A12: P008 | B12: Pão de queijo congelado 1 kg | C12: Congelados | D12: kg | E12: 18 | F12: 32 | G12: 10 | H12: 5 | I12: =IF(A12="","",SUMIFS('Movimentações'!$E$5:$E$5000,'Movimentações'!$B$5:$B$5000,A12,'Movimentações'!$D$5:$D$5000,"Entrada")) | J12: =IF(A12="","",SUMIFS('Movimentações'!$E$5:$E$5000,'Movimentações'!$B$5:$B$5000,A12,'Movimentações'!$D$5:$D$5000,"Saída")) | K12: =IF(A12="","",G12+I12-J12) | L12: =IF(A12="","",IF(K12<=0,"SEM ESTOQUE",IF(K12<=H12,"REPOR","OK"))) | M12: =IF(A12="","",MAX(K12,0)*E12) | N12: =IF(A12="","",IF(K12<=H12,MAX(2*H12-K12,0),0)) | O12: =IF(OR(A12="",F12=0,F12=""),"",(F12-E12)/F12)
I13: =IF(A13="","",SUMIFS('Movimentações'!$E$5:$E$5000,'Movimentações'!$B$5:$B$5000,A13,'Movimentações'!$D$5:$D$5000,"Entrada")) | J13: =IF(A13="","",SUMIFS('Movimentações'!$E$5:$E$5000,'Movimentações'!$B$5:$B$5000,A13,'Movimentações'!$D$5:$D$5000,"Saída")) | K13: =IF(A13="","",G13+I13-J13) | L13: =IF(A13="","",IF(K13<=0,"SEM ESTOQUE",IF(K13<=H13,"REPOR","OK"))) | M13: =IF(A13="","",MAX(K13,0)*E13) | N13: =IF(A13="","",IF(K13<=H13,MAX(2*H13-K13,0),0)) | O13: =IF(OR(A13="",F13=0,F13=""),"",(F13-E13)/F13)
I14: =IF(A14="","",SUMIFS('Movimentações'!$E$5:$E$5000,'Movimentações'!$B$5:$B$5000,A14,'Movimentações'!$D$5:$D$5000,"Entrada")) | J14: =IF(A14="","",SUMIFS('Movimentações'!$E$5:$E$5000,'Movimentações'!$B$5:$B$5000,A14,'Movimentações'!$D$5:$D$5000,"Saída")) | K14: =IF(A14="","",G14+I14-J14) | L14: =IF(A14="","",IF(K14<=0,"SEM ESTOQUE",IF(K14<=H14,"REPOR","OK"))) | M14: =IF(A14="","",MAX(K14,0)*E14) | N14: =IF(A14="","",IF(K14<=H14,MAX(2*H14-K14,0),0)) | O14: =IF(OR(A14="",F14=0,F14=""),"",(F14-E14)/F14)
I15: =IF(A15="","",SUMIFS('Movimentações'!$E$5:$E$5000,'Movimentações'!$B$5:$B$5000,A15,'Movimentações'!$D$5:$D$5000,"Entrada")) | J15: =IF(A15="","",SUMIFS('Movimentações'!$E$5:$E$5000,'Movimentações'!$B$5:$B$5000,A15,'Movimentações'!$D$5:$D$5000,"Saída")) | K15: =IF(A15="","",G15+I15-J15) | L15: =IF(A15="","",IF(K15<=0,"SEM ESTOQUE",IF(K15<=H15,"REPOR","OK"))) | M15: =IF(A15="","",MAX(K15,0)*E15) | N15: =IF(A15="","",IF(K15<=H15,MAX(2*H15-K15,0),0)) | O15: =IF(OR(A15="",F15=0,F15=""),"",(F15-E15)/F15)
I16: =IF(A16="","",SUMIFS('Movimentações'!$E$5:$E$5000,'Movimentações'!$B$5:$B$5000,A16,'Movimentações'!$D$5:$D$5000,"Entrada")) | J16: =IF(A16="","",SUMIFS('Movimentações'!$E$5:$E$5000,'Movimentações'!$B$5:$B$5000,A16,'Movimentações'!$D$5:$D$5000,"Saída")) | K16: =IF(A16="","",G16+I16-J16) | L16: =IF(A16="","",IF(K16<=0,"SEM ESTOQUE",IF(K16<=H16,"REPOR","OK"))) | M16: =IF(A16="","",MAX(K16,0)*E16) | N16: =IF(A16="","",IF(K16<=H16,MAX(2*H16-K16,0),0)) | O16: =IF(OR(A16="",F16=0,F16=""),"",(F16-E16)/F16)
I17: =IF(A17="","",SUMIFS('Movimentações'!$E$5:$E$5000,'Movimentações'!$B$5:$B$5000,A17,'Movimentações'!$D$5:$D$5000,"Entrada")) | J17: =IF(A17="","",SUMIFS('Movimentações'!$E$5:$E$5000,'Movimentações'!$B$5:$B$5000,A17,'Movimentações'!$D$5:$D$5000,"Saída")) | K17: =IF(A17="","",G17+I17-J17) | L17: =IF(A17="","",IF(K17<=0,"SEM ESTOQUE",IF(K17<=H17,"REPOR","OK"))) | M17: =IF(A17="","",MAX(K17,0)*E17) | N17: =IF(A17="","",IF(K17<=H17,MAX(2*H17-K17,0),0)) | O17: =IF(OR(A17="",F17=0,F17=""),"",(F17-E17)/F17)
I18: =IF(A18="","",SUMIFS('Movimentações'!$E$5:$E$5000,'Movimentações'!$B$5:$B$5000,A18,'Movimentações'!$D$5:$D$5000,"Entrada")) | J18: =IF(A18="","",SUMIFS('Movimentações'!$E$5:$E$5000,'Movimentações'!$B$5:$B$5000,A18,'Movimentações'!$D$5:$D$5000,"Saída")) | K18: =IF(A18="","",G18+I18-J18) | L18: =IF(A18="","",IF(K18<=0,"SEM ESTOQUE",IF(K18<=H18,"REPOR","OK"))) | M18: =IF(A18="","",MAX(K18,0)*E18) | N18: =IF(A18="","",IF(K18<=H18,MAX(2*H18-K18,0),0)) | O18: =IF(OR(A18="",F18=0,F18=""),"",(F18-E18)/F18)
I19: =IF(A19="","",SUMIFS('Movimentações'!$E$5:$E$5000,'Movimentações'!$B$5:$B$5000,A19,'Movimentações'!$D$5:$D$5000,"Entrada")) | J19: =IF(A19="","",SUMIFS('Movimentações'!$E$5:$E$5000,'Movimentações'!$B$5:$B$5000,A19,'Movimentações'!$D$5:$D$5000,"Saída")) | K19: =IF(A19="","",G19+I19-J19) | L19: =IF(A19="","",IF(K19<=0,"SEM ESTOQUE",IF(K19<=H19,"REPOR","OK"))) | M19: =IF(A19="","",MAX(K19,0)*E19) | N19: =IF(A19="","",IF(K19<=H19,MAX(2*H19-K19,0),0)) | O19: =IF(OR(A19="",F19=0,F19=""),"",(F19-E19)/F19)
I20: =IF(A20="","",SUMIFS('Movimentações'!$E$5:$E$5000,'Movimentações'!$B$5:$B$5000,A20,'Movimentações'!$D$5:$D$5000,"Entrada")) | J20: =IF(A20="","",SUMIFS('Movimentações'!$E$5:$E$5000,'Movimentações'!$B$5:$B$5000,A20,'Movimentações'!$D$5:$D$5000,"Saída")) | K20: =IF(A20="","",G20+I20-J20) | L20: =IF(A20="","",IF(K20<=0,"SEM ESTOQUE",IF(K20<=H20,"REPOR","OK"))) | M20: =IF(A20="","",MAX(K20,0)*E20) | N20: =IF(A20="","",IF(K20<=H20,MAX(2*H20-K20,0),0)) | O20: =IF(OR(A20="",F20=0,F20=""),"",(F20-E20)/F20)
I21: =IF(A21="","",SUMIFS('Movimentações'!$E$5:$E$5000,'Movimentações'!$B$5:$B$5000,A21,'Movimentações'!$D$5:$D$5000,"Entrada")) | J21: =IF(A21="","",SUMIFS('Movimentações'!$E$5:$E$5000,'Movimentações'!$B$5:$B$5000,A21,'Movimentações'!$D$5:$D$5000,"Saída")) | K21: =IF(A21="","",G21+I21-J21) | L21: =IF(A21="","",IF(K21<=0,"SEM ESTOQUE",IF(K21<=H21,"REPOR","OK"))) | M21: =IF(A21="","",MAX(K21,0)*E21) | N21: =IF(A21="","",IF(K21<=H21,MAX(2*H21-K21,0),0)) | O21: =IF(OR(A21="",F21=0,F21=""),"",(F21-E21)/F21)
I22: =IF(A22="","",SUMIFS('Movimentações'!$E$5:$E$5000,'Movimentações'!$B$5:$B$5000,A22,'Movimentações'!$D$5:$D$5000,"Entrada")) | J22: =IF(A22="","",SUMIFS('Movimentações'!$E$5:$E$5000,'Movimentações'!$B$5:$B$5000,A22,'Movimentações'!$D$5:$D$5000,"Saída")) | K22: =IF(A22="","",G22+I22-J22) | L22: =IF(A22="","",IF(K22<=0,"SEM ESTOQUE",IF(K22<=H22,"REPOR","OK"))) | M22: =IF(A22="","",MAX(K22,0)*E22) | N22: =IF(A22="","",IF(K22<=H22,MAX(2*H22-K22,0),0)) | O22: =IF(OR(A22="",F22=0,F22=""),"",(F22-E22)/F22)
I23: =IF(A23="","",SUMIFS('Movimentações'!$E$5:$E$5000,'Movimentações'!$B$5:$B$5000,A23,'Movimentações'!$D$5:$D$5000,"Entrada")) | J23: =IF(A23="","",SUMIFS('Movimentações'!$E$5:$E$5000,'Movimentações'!$B$5:$B$5000,A23,'Movimentações'!$D$5:$D$5000,"Saída")) | K23: =IF(A23="","",G23+I23-J23) | L23: =IF(A23="","",IF(K23<=0,"SEM ESTOQUE",IF(K23<=H23,"REPOR","OK"))) | M23: =IF(A23="","",MAX(K23,0)*E23) | N23: =IF(A23="","",IF(K23<=H23,MAX(2*H23-K23,0),0)) | O23: =IF(OR(A23="",F23=0,F23=""),"",(F23-E23)/F23)
I24: =IF(A24="","",SUMIFS('Movimentações'!$E$5:$E$5000,'Movimentações'!$B$5:$B$5000,A24,'Movimentações'!$D$5:$D$5000,"Entrada")) | J24: =IF(A24="","",SUMIFS('Movimentações'!$E$5:$E$5000,'Movimentações'!$B$5:$B$5000,A24,'Movimentações'!$D$5:$D$5000,"Saída")) | K24: =IF(A24="","",G24+I24-J24) | L24: =IF(A24="","",IF(K24<=0,"SEM ESTOQUE",IF(K24<=H24,"REPOR","OK"))) | M24: =IF(A24="","",MAX(K24,0)*E24) | N24: =IF(A24="","",IF(K24<=H24,MAX(2*H24-K24,0),0)) | O24: =IF(OR(A24="",F24=0,F24=""),"",(F24-E24)/F24)
... I504: =IF(A504="","",SUMIFS('Movimentações'!$E$5:$E$5000,'Movimentações'!$B$5:$B$5000,A504,'Movimentações'!$D$5:$D$5000,"Entrada")) | J504: =IF(A504="","",SUMIFS('Movimentações'!$E$5:$E$5000,'Movimentações'!$B$5:$B$5000,A504,'Movimentações'!$D$5:$D$5000,"Saída")) | K504: =IF(A504="","",G504+I504-J504) | L504: =IF(A504="","",IF(K504<=0,"SEM ESTOQUE",IF(K504<=H504,"REPOR","OK"))) | M504: =IF(A504="","",MAX(K504,0)*E504) | N504: =IF(A504="","",IF(K504<=H504,MAX(2*H504-K504,0),0)) | O504: =IF(OR(A504="",F504=0,F504=""),"",(F504-E504)/F504)

Sheet Movimentações
A1: Movimentações
A2: Uma linha para cada entrada ou saída de produto.
A4: Data | B4: Código | C4: Produto | D4: Tipo | E4: Quantidade | F4: Observação
A5: =TODAY()+(-20) | B5: P001 | C5: =IF(B5="","",IFERROR(VLOOKUP(B5,Produtos!$A$5:$B$504,2,FALSE),"código não cadastrado")) | D5: Saída | E5: 12 | F5: vendas da semana
A6: =TODAY()+(-18) | B6: P003 | C6: =IF(B6="","",IFERROR(VLOOKUP(B6,Produtos!$A$5:$B$504,2,FALSE),"código não cadastrado")) | D6: Saída | E6: 22 | F6: vendas da semana
A7: =TODAY()+(-15) | B7: P002 | C7: =IF(B7="","",IFERROR(VLOOKUP(B7,Produtos!$A$5:$B$504,2,FALSE),"código não cadastrado")) | D7: Saída | E7: 9
A8: =TODAY()+(-14) | B8: P004 | C8: =IF(B8="","",IFERROR(VLOOKUP(B8,Produtos!$A$5:$B$504,2,FALSE),"código não cadastrado")) | D8: Saída | E8: 7 | F8: evento
A9: =TODAY()+(-12) | B9: P001 | C9: =IF(B9="","",IFERROR(VLOOKUP(B9,Produtos!$A$5:$B$504,2,FALSE),"código não cadastrado")) | D9: Entrada | E9: 10 | F9: compra fornecedor A
A10: =TODAY()+(-10) | B10: P006 | C10: =IF(B10="","",IFERROR(VLOOKUP(B10,Produtos!$A$5:$B$504,2,FALSE),"código não cadastrado")) | D10: Saída | E10: 5
A11: =TODAY()+(-9) | B11: P008 | C11: =IF(B11="","",IFERROR(VLOOKUP(B11,Produtos!$A$5:$B$504,2,FALSE),"código não cadastrado")) | D11: Saída | E11: 6
A12: =TODAY()+(-7) | B12: P003 | C12: =IF(B12="","",IFERROR(VLOOKUP(B12,Produtos!$A$5:$B$504,2,FALSE),"código não cadastrado")) | D12: Saída | E12: 18
A13: =TODAY()+(-6) | B13: P005 | C13: =IF(B13="","",IFERROR(VLOOKUP(B13,Produtos!$A$5:$B$504,2,FALSE),"código não cadastrado")) | D13: Saída | E13: 8
A14: =TODAY()+(-5) | B14: P007 | C14: =IF(B14="","",IFERROR(VLOOKUP(B14,Produtos!$A$5:$B$504,2,FALSE),"código não cadastrado")) | D14: Saída | E14: 4
A15: =TODAY()+(-3) | B15: P002 | C15: =IF(B15="","",IFERROR(VLOOKUP(B15,Produtos!$A$5:$B$504,2,FALSE),"código não cadastrado")) | D15: Entrada | E15: 12 | F15: compra fornecedor B
A16: =TODAY()+(-2) | B16: P004 | C16: =IF(B16="","",IFERROR(VLOOKUP(B16,Produtos!$A$5:$B$504,2,FALSE),"código não cadastrado")) | D16: Saída | E16: 5
A17: =TODAY()+(-1) | B17: P008 | C17: =IF(B17="","",IFERROR(VLOOKUP(B17,Produtos!$A$5:$B$504,2,FALSE),"código não cadastrado")) | D17: Saída | E17: 4
A18: =TODAY()+(-1) | B18: P001 | C18: =IF(B18="","",IFERROR(VLOOKUP(B18,Produtos!$A$5:$B$504,2,FALSE),"código não cadastrado")) | D18: Saída | E18: 14
C19: =IF(B19="","",IFERROR(VLOOKUP(B19,Produtos!$A$5:$B$504,2,FALSE),"código não cadastrado"))
C20: =IF(B20="","",IFERROR(VLOOKUP(B20,Produtos!$A$5:$B$504,2,FALSE),"código não cadastrado"))
C21: =IF(B21="","",IFERROR(VLOOKUP(B21,Produtos!$A$5:$B$504,2,FALSE),"código não cadastrado"))
C22: =IF(B22="","",IFERROR(VLOOKUP(B22,Produtos!$A$5:$B$504,2,FALSE),"código não cadastrado"))
C23: =IF(B23="","",IFERROR(VLOOKUP(B23,Produtos!$A$5:$B$504,2,FALSE),"código não cadastrado"))
C24: =IF(B24="","",IFERROR(VLOOKUP(B24,Produtos!$A$5:$B$504,2,FALSE),"código não cadastrado"))
C25: =IF(B25="","",IFERROR(VLOOKUP(B25,Produtos!$A$5:$B$504,2,FALSE),"código não cadastrado"))
C26: =IF(B26="","",IFERROR(VLOOKUP(B26,Produtos!$A$5:$B$504,2,FALSE),"código não cadastrado"))
C27: =IF(B27="","",IFERROR(VLOOKUP(B27,Produtos!$A$5:$B$504,2,FALSE),"código não cadastrado"))
C28: =IF(B28="","",IFERROR(VLOOKUP(B28,Produtos!$A$5:$B$504,2,FALSE),"código não cadastrado"))
C29: =IF(B29="","",IFERROR(VLOOKUP(B29,Produtos!$A$5:$B$504,2,FALSE),"código não cadastrado"))
C30: =IF(B30="","",IFERROR(VLOOKUP(B30,Produtos!$A$5:$B$504,2,FALSE),"código não cadastrado"))
... C504: =IF(B504="","",IFERROR(VLOOKUP(B504,Produtos!$A$5:$B$504,2,FALSE),"código não cadastrado"))
