Workbook

Sheet Como usar
A1: Kit de Arranque · Controle de Vencimentos
A2: Resolvo Já · resolvoja.com
B4: Passo a passo
A5: 1 | B5: Na aba Vencimentos, liste tudo que tem data: impostos e guias, contas fixas, contratos, alvarás e licenças, certificado digital, seguros, mensalidades de sistemas.
A6: 2 | B6: Preencha a Data de vencimento e, em Avisar com, quantos dias antes você quer ser alertado (padrão: 7).
A7: 3 | B7: A Situação se atualiza todo dia sozinha: vermelho = VENCIDO, amarelo = VENCE EM BREVE, verde = no prazo.
A8: 4 | B8: Quando pagar ou renovar, mude o Status para Feito. Se for recorrente, a coluna Próximo vencimento mostra a nova data: lance uma nova linha com ela.
A9: 5 | B9: Abra a planilha toda segunda-feira e olhe o Painel: ele mostra o que vence nos próximos 7 e 30 dias e quanto vai sair do caixa.
B11: Legenda das colunas
B12: Cabeçalho azul escuro: você preenche.
B13: Cabeçalho azul claro: calculado automaticamente, não precisa mexer.
B15: Dicas
B16: • As datas de impostos (DAS, DARF, guias estaduais e municipais) mudam conforme o regime e a cidade. Confirme as suas com o seu contador antes de cadastrar.
B17: • Certificado digital e alvarás costumam levar dias para renovar: use um aviso maior (30 dias) para eles.
B18: • Use a coluna Responsável quando mais de uma pessoa cuida das contas.
B20: Os dados que já vêm na planilha são exemplos para você ver tudo funcionando. Apague o conteúdo das linhas de exemplo (só as colunas de cabeçalho escuro) e comece a usar.

Sheet Painel
A1: Painel de Vencimentos
A2: Atualiza sozinho conforme você preenche as outras abas.
A4: Itens VENCIDOS | B4: =COUNTIF(Vencimentos!$J$5:$J$504,"VENCIDO")
A5: Itens que VENCEM EM BREVE | B5: =COUNTIF(Vencimentos!$J$5:$J$504,"VENCE EM BREVE")
A6: Valor vencido e não pago | B6: =SUMIFS(Vencimentos!$E$5:$E$504,Vencimentos!$J$5:$J$504,"VENCIDO")
A7: A pagar nos próximos 7 dias | B7: =SUMIFS(Vencimentos!$E$5:$E$504,Vencimentos!$D$5:$D$504,">="&TODAY(),Vencimentos!$D$5:$D$504,"<="&(TODAY()+7),Vencimentos!$H$5:$H$504,"<>Feito")
A8: A pagar nos próximos 30 dias | B8: =SUMIFS(Vencimentos!$E$5:$E$504,Vencimentos!$D$5:$D$504,">="&TODAY(),Vencimentos!$D$5:$D$504,"<="&(TODAY()+30),Vencimentos!$H$5:$H$504,"<>Feito")
A9: Itens pendentes cadastrados | B9: =SUMPRODUCT((Vencimentos!$A$5:$A$504<>"")*(Vencimentos!$H$5:$H$504<>"Feito"))

Sheet Vencimentos
A1: Vencimentos
A2: Tudo que tem prazo: impostos, contas, contratos, licenças.
A4: Item | B4: Categoria | C4: Responsável | D4: Data de vencimento | E4: Valor | F4: Recorrência | G4: Avisar com (dias) | H4: Status | I4: Dias restantes | J4: Situação | K4: Próximo vencimento | L4: Observação
A5: DAS (Simples Nacional) | B5: Imposto / guia | C5: Contador | D5: =TODAY()+(5) | E5: 412.35 | F5: Mensal | G5: 5 | H5: Pendente | I5: =IF(OR(A5="",D5="",H5="Feito"),"",D5-TODAY()) | J5: =IF(OR(A5="",D5=""),"",IF(H5="Feito","FEITO",IF(I5<0,"VENCIDO",IF(I5<=IF(G5="",7,G5),"VENCE EM BREVE","No prazo")))) | K5: =IF(OR(D5="",F5="",F5="Única"),"",EDATE(D5,IF(F5="Mensal",1,IF(F5="Trimestral",3,IF(F5="Semestral",6,12))))) | L5: conferir valor com o contador
A6: Aluguel da loja | B6: Conta fixa | C6: Sócio | D6: =TODAY()+(2) | E6: 2800 | F6: Mensal | G6: 5 | H6: Pendente | I6: =IF(OR(A6="",D6="",H6="Feito"),"",D6-TODAY()) | J6: =IF(OR(A6="",D6=""),"",IF(H6="Feito","FEITO",IF(I6<0,"VENCIDO",IF(I6<=IF(G6="",7,G6),"VENCE EM BREVE","No prazo")))) | K6: =IF(OR(D6="",F6="",F6="Única"),"",EDATE(D6,IF(F6="Mensal",1,IF(F6="Trimestral",3,IF(F6="Semestral",6,12)))))
A7: Energia elétrica | B7: Conta fixa | C7: Sócio | D7: =TODAY()+(-1) | E7: 389.9 | F7: Mensal | G7: 3 | H7: Pendente | I7: =IF(OR(A7="",D7="",H7="Feito"),"",D7-TODAY()) | J7: =IF(OR(A7="",D7=""),"",IF(H7="Feito","FEITO",IF(I7<0,"VENCIDO",IF(I7<=IF(G7="",7,G7),"VENCE EM BREVE","No prazo")))) | K7: =IF(OR(D7="",F7="",F7="Única"),"",EDATE(D7,IF(F7="Mensal",1,IF(F7="Trimestral",3,IF(F7="Semestral",6,12)))))
A8: Internet | B8: Conta fixa | C8: Sócio | D8: =TODAY()+(12) | E8: 129.9 | F8: Mensal | G8: 3 | H8: Pendente | I8: =IF(OR(A8="",D8="",H8="Feito"),"",D8-TODAY()) | J8: =IF(OR(A8="",D8=""),"",IF(H8="Feito","FEITO",IF(I8<0,"VENCIDO",IF(I8<=IF(G8="",7,G8),"VENCE EM BREVE","No prazo")))) | K8: =IF(OR(D8="",F8="",F8="Única"),"",EDATE(D8,IF(F8="Mensal",1,IF(F8="Trimestral",3,IF(F8="Semestral",6,12)))))
A9: Certificado digital A1 | B9: Certificado digital | C9: Sócio | D9: =TODAY()+(25) | E9: 220 | F9: Anual | G9: 30 | H9: Pendente | I9: =IF(OR(A9="",D9="",H9="Feito"),"",D9-TODAY()) | J9: =IF(OR(A9="",D9=""),"",IF(H9="Feito","FEITO",IF(I9<0,"VENCIDO",IF(I9<=IF(G9="",7,G9),"VENCE EM BREVE","No prazo")))) | K9: =IF(OR(D9="",F9="",F9="Única"),"",EDATE(D9,IF(F9="Mensal",1,IF(F9="Trimestral",3,IF(F9="Semestral",6,12))))) | L9: renovar com antecedência
A10: Alvará de funcionamento | B10: Alvará / licença | C10: Contador | D10: =TODAY()+(60) | E10: 0 | F10: Anual | G10: 30 | H10: Pendente | I10: =IF(OR(A10="",D10="",H10="Feito"),"",D10-TODAY()) | J10: =IF(OR(A10="",D10=""),"",IF(H10="Feito","FEITO",IF(I10<0,"VENCIDO",IF(I10<=IF(G10="",7,G10),"VENCE EM BREVE","No prazo")))) | K10: =IF(OR(D10="",F10="",F10="Única"),"",EDATE(D10,IF(F10="Mensal",1,IF(F10="Trimestral",3,IF(F10="Semestral",6,12)))))
A11: Contrato do sistema de vendas | B11: Sistema / assinatura | C11: Sócio | D11: =TODAY()+(40) | E11: 99 | F11: Mensal | G11: 7 | H11: Pendente | I11: =IF(OR(A11="",D11="",H11="Feito"),"",D11-TODAY()) | J11: =IF(OR(A11="",D11=""),"",IF(H11="Feito","FEITO",IF(I11<0,"VENCIDO",IF(I11<=IF(G11="",7,G11),"VENCE EM BREVE","No prazo")))) | K11: =IF(OR(D11="",F11="",F11="Única"),"",EDATE(D11,IF(F11="Mensal",1,IF(F11="Trimestral",3,IF(F11="Semestral",6,12)))))
A12: Seguro do estabelecimento | B12: Seguro | C12: Sócio | D12: =TODAY()+(-10) | E12: 1450 | F12: Anual | G12: 15 | H12: Feito | I12: =IF(OR(A12="",D12="",H12="Feito"),"",D12-TODAY()) | J12: =IF(OR(A12="",D12=""),"",IF(H12="Feito","FEITO",IF(I12<0,"VENCIDO",IF(I12<=IF(G12="",7,G12),"VENCE EM BREVE","No prazo")))) | K12: =IF(OR(D12="",F12="",F12="Única"),"",EDATE(D12,IF(F12="Mensal",1,IF(F12="Trimestral",3,IF(F12="Semestral",6,12))))) | L12: renovado
I13: =IF(OR(A13="",D13="",H13="Feito"),"",D13-TODAY()) | J13: =IF(OR(A13="",D13=""),"",IF(H13="Feito","FEITO",IF(I13<0,"VENCIDO",IF(I13<=IF(G13="",7,G13),"VENCE EM BREVE","No prazo")))) | K13: =IF(OR(D13="",F13="",F13="Única"),"",EDATE(D13,IF(F13="Mensal",1,IF(F13="Trimestral",3,IF(F13="Semestral",6,12)))))
I14: =IF(OR(A14="",D14="",H14="Feito"),"",D14-TODAY()) | J14: =IF(OR(A14="",D14=""),"",IF(H14="Feito","FEITO",IF(I14<0,"VENCIDO",IF(I14<=IF(G14="",7,G14),"VENCE EM BREVE","No prazo")))) | K14: =IF(OR(D14="",F14="",F14="Única"),"",EDATE(D14,IF(F14="Mensal",1,IF(F14="Trimestral",3,IF(F14="Semestral",6,12)))))
I15: =IF(OR(A15="",D15="",H15="Feito"),"",D15-TODAY()) | J15: =IF(OR(A15="",D15=""),"",IF(H15="Feito","FEITO",IF(I15<0,"VENCIDO",IF(I15<=IF(G15="",7,G15),"VENCE EM BREVE","No prazo")))) | K15: =IF(OR(D15="",F15="",F15="Única"),"",EDATE(D15,IF(F15="Mensal",1,IF(F15="Trimestral",3,IF(F15="Semestral",6,12)))))
I16: =IF(OR(A16="",D16="",H16="Feito"),"",D16-TODAY()) | J16: =IF(OR(A16="",D16=""),"",IF(H16="Feito","FEITO",IF(I16<0,"VENCIDO",IF(I16<=IF(G16="",7,G16),"VENCE EM BREVE","No prazo")))) | K16: =IF(OR(D16="",F16="",F16="Única"),"",EDATE(D16,IF(F16="Mensal",1,IF(F16="Trimestral",3,IF(F16="Semestral",6,12)))))
I17: =IF(OR(A17="",D17="",H17="Feito"),"",D17-TODAY()) | J17: =IF(OR(A17="",D17=""),"",IF(H17="Feito","FEITO",IF(I17<0,"VENCIDO",IF(I17<=IF(G17="",7,G17),"VENCE EM BREVE","No prazo")))) | K17: =IF(OR(D17="",F17="",F17="Única"),"",EDATE(D17,IF(F17="Mensal",1,IF(F17="Trimestral",3,IF(F17="Semestral",6,12)))))
I18: =IF(OR(A18="",D18="",H18="Feito"),"",D18-TODAY()) | J18: =IF(OR(A18="",D18=""),"",IF(H18="Feito","FEITO",IF(I18<0,"VENCIDO",IF(I18<=IF(G18="",7,G18),"VENCE EM BREVE","No prazo")))) | K18: =IF(OR(D18="",F18="",F18="Única"),"",EDATE(D18,IF(F18="Mensal",1,IF(F18="Trimestral",3,IF(F18="Semestral",6,12)))))
I19: =IF(OR(A19="",D19="",H19="Feito"),"",D19-TODAY()) | J19: =IF(OR(A19="",D19=""),"",IF(H19="Feito","FEITO",IF(I19<0,"VENCIDO",IF(I19<=IF(G19="",7,G19),"VENCE EM BREVE","No prazo")))) | K19: =IF(OR(D19="",F19="",F19="Única"),"",EDATE(D19,IF(F19="Mensal",1,IF(F19="Trimestral",3,IF(F19="Semestral",6,12)))))
I20: =IF(OR(A20="",D20="",H20="Feito"),"",D20-TODAY()) | J20: =IF(OR(A20="",D20=""),"",IF(H20="Feito","FEITO",IF(I20<0,"VENCIDO",IF(I20<=IF(G20="",7,G20),"VENCE EM BREVE","No prazo")))) | K20: =IF(OR(D20="",F20="",F20="Única"),"",EDATE(D20,IF(F20="Mensal",1,IF(F20="Trimestral",3,IF(F20="Semestral",6,12)))))
I21: =IF(OR(A21="",D21="",H21="Feito"),"",D21-TODAY()) | J21: =IF(OR(A21="",D21=""),"",IF(H21="Feito","FEITO",IF(I21<0,"VENCIDO",IF(I21<=IF(G21="",7,G21),"VENCE EM BREVE","No prazo")))) | K21: =IF(OR(D21="",F21="",F21="Única"),"",EDATE(D21,IF(F21="Mensal",1,IF(F21="Trimestral",3,IF(F21="Semestral",6,12)))))
I22: =IF(OR(A22="",D22="",H22="Feito"),"",D22-TODAY()) | J22: =IF(OR(A22="",D22=""),"",IF(H22="Feito","FEITO",IF(I22<0,"VENCIDO",IF(I22<=IF(G22="",7,G22),"VENCE EM BREVE","No prazo")))) | K22: =IF(OR(D22="",F22="",F22="Única"),"",EDATE(D22,IF(F22="Mensal",1,IF(F22="Trimestral",3,IF(F22="Semestral",6,12)))))
I23: =IF(OR(A23="",D23="",H23="Feito"),"",D23-TODAY()) | J23: =IF(OR(A23="",D23=""),"",IF(H23="Feito","FEITO",IF(I23<0,"VENCIDO",IF(I23<=IF(G23="",7,G23),"VENCE EM BREVE","No prazo")))) | K23: =IF(OR(D23="",F23="",F23="Única"),"",EDATE(D23,IF(F23="Mensal",1,IF(F23="Trimestral",3,IF(F23="Semestral",6,12)))))
I24: =IF(OR(A24="",D24="",H24="Feito"),"",D24-TODAY()) | J24: =IF(OR(A24="",D24=""),"",IF(H24="Feito","FEITO",IF(I24<0,"VENCIDO",IF(I24<=IF(G24="",7,G24),"VENCE EM BREVE","No prazo")))) | K24: =IF(OR(D24="",F24="",F24="Única"),"",EDATE(D24,IF(F24="Mensal",1,IF(F24="Trimestral",3,IF(F24="Semestral",6,12)))))
... I504: =IF(OR(A504="",D504="",H504="Feito"),"",D504-TODAY()) | J504: =IF(OR(A504="",D504=""),"",IF(H504="Feito","FEITO",IF(I504<0,"VENCIDO",IF(I504<=IF(G504="",7,G504),"VENCE EM BREVE","No prazo")))) | K504: =IF(OR(D504="",F504="",F504="Única"),"",EDATE(D504,IF(F504="Mensal",1,IF(F504="Trimestral",3,IF(F504="Semestral",6,12)))))
