Workbook

Sheet Como usar
A1: Kit de Arranque · Gestão de Pedidos
A2: Resolvo Já · resolvoja.com
B4: Passo a passo
A5: 1 | B5: Na aba Catálogo, cadastre seus produtos ou serviços com o preço de venda.
A6: 2 | B6: Na aba Pedidos, registre cada pedido. Se o pedido tiver mais de um produto, use uma linha por produto repetindo o mesmo Nº do pedido.
A7: 3 | B7: Escolha o produto na lista: o preço aparece sozinho e o total é calculado (quantidade × preço − desconto).
A8: 4 | B8: Atualize a coluna Status conforme o pedido anda: Novo → Em produção → Pronto → Entregue. Pedidos com entrega vencida e ainda não entregues ficam marcados em vermelho como ATRASADO.
A9: 5 | B9: No Painel, digite o mês e o ano que quer analisar e veja faturamento, valores a receber e os produtos mais vendidos.
B11: Legenda das colunas
B12: Cabeçalho azul escuro: você preenche.
B13: Cabeçalho azul claro: calculado automaticamente, não precisa mexer.
B15: Dicas
B16: • Marque Pago = Sim só quando o dinheiro entrar. O Painel mostra quanto ainda falta receber.
B17: • Pedidos cancelados não entram no faturamento, mas continuam registrados para você entender os motivos.
B18: • Reveja todo dia de manhã os pedidos com entrega para hoje e para amanhã (dá para filtrar a coluna Entrega).
B20: Os dados que já vêm na planilha são exemplos para você ver tudo funcionando. Apague o conteúdo das linhas de exemplo (só as colunas de cabeçalho escuro) e comece a usar.

Sheet Painel
A1: Painel de Pedidos
A2: Atualiza sozinho conforme você preenche as outras abas.
A4: Mês (1 a 12) | B4: =MONTH(TODAY()) | C4: ← troque pelo mês que quer ver (a fórmula padrão mostra o mês atual)
A5: Ano | B5: =YEAR(TODAY())
A7: Faturamento do mês (sem cancelados) | B7: =SUMIFS(Pedidos!$I$5:$I$504,Pedidos!$B$5:$B$504,">="&DATE($B$5,$B$4,1),Pedidos!$B$5:$B$504,"<"&DATE($B$5,$B$4+1,1),Pedidos!$M$5:$M$504,"<>Cancelado")
A8: A receber no mês (Pago = Não) | B8: =SUMIFS(Pedidos!$I$5:$I$504,Pedidos!$B$5:$B$504,">="&DATE($B$5,$B$4,1),Pedidos!$B$5:$B$504,"<"&DATE($B$5,$B$4+1,1),Pedidos!$M$5:$M$504,"<>Cancelado",Pedidos!$L$5:$L$504,"Não")
A9: Itens vendidos no mês | B9: =SUMIFS(Pedidos!$F$5:$F$504,Pedidos!$B$5:$B$504,">="&DATE($B$5,$B$4,1),Pedidos!$B$5:$B$504,"<"&DATE($B$5,$B$4+1,1),Pedidos!$M$5:$M$504,"<>Cancelado")
A10: Linhas canceladas no mês | B10: =COUNTIFS(Pedidos!$B$5:$B$504,">="&DATE($B$5,$B$4,1),Pedidos!$B$5:$B$504,"<"&DATE($B$5,$B$4+1,1),Pedidos!$M$5:$M$504,"Cancelado")
A11: Pedidos em aberto (todas as datas) | B11: =SUMPRODUCT((Pedidos!$E$5:$E$504<>"")*(Pedidos!$M$5:$M$504<>"Entregue")*(Pedidos!$M$5:$M$504<>"Cancelado"))
A12: Linhas ATRASADAS agora | B12: =COUNTIF(Pedidos!$N$5:$N$504,"ATRASADO")
A15: Vendas por produto no mês
A16: Produto / serviço | B16: Quantidade | C16: Faturamento
A17: =IF('Catálogo'!A5="","",'Catálogo'!A5) | B17: =IF(A17="","",SUMIFS(Pedidos!$F$5:$F$504,Pedidos!$E$5:$E$504,A17,Pedidos!$B$5:$B$504,">="&DATE($B$5,$B$4,1),Pedidos!$B$5:$B$504,"<"&DATE($B$5,$B$4+1,1),Pedidos!$M$5:$M$504,"<>Cancelado")) | C17: =IF(A17="","",SUMIFS(Pedidos!$I$5:$I$504,Pedidos!$E$5:$E$504,A17,Pedidos!$B$5:$B$504,">="&DATE($B$5,$B$4,1),Pedidos!$B$5:$B$504,"<"&DATE($B$5,$B$4+1,1),Pedidos!$M$5:$M$504,"<>Cancelado"))
A18: =IF('Catálogo'!A6="","",'Catálogo'!A6) | B18: =IF(A18="","",SUMIFS(Pedidos!$F$5:$F$504,Pedidos!$E$5:$E$504,A18,Pedidos!$B$5:$B$504,">="&DATE($B$5,$B$4,1),Pedidos!$B$5:$B$504,"<"&DATE($B$5,$B$4+1,1),Pedidos!$M$5:$M$504,"<>Cancelado")) | C18: =IF(A18="","",SUMIFS(Pedidos!$I$5:$I$504,Pedidos!$E$5:$E$504,A18,Pedidos!$B$5:$B$504,">="&DATE($B$5,$B$4,1),Pedidos!$B$5:$B$504,"<"&DATE($B$5,$B$4+1,1),Pedidos!$M$5:$M$504,"<>Cancelado"))
A19: =IF('Catálogo'!A7="","",'Catálogo'!A7) | B19: =IF(A19="","",SUMIFS(Pedidos!$F$5:$F$504,Pedidos!$E$5:$E$504,A19,Pedidos!$B$5:$B$504,">="&DATE($B$5,$B$4,1),Pedidos!$B$5:$B$504,"<"&DATE($B$5,$B$4+1,1),Pedidos!$M$5:$M$504,"<>Cancelado")) | C19: =IF(A19="","",SUMIFS(Pedidos!$I$5:$I$504,Pedidos!$E$5:$E$504,A19,Pedidos!$B$5:$B$504,">="&DATE($B$5,$B$4,1),Pedidos!$B$5:$B$504,"<"&DATE($B$5,$B$4+1,1),Pedidos!$M$5:$M$504,"<>Cancelado"))
A20: =IF('Catálogo'!A8="","",'Catálogo'!A8) | B20: =IF(A20="","",SUMIFS(Pedidos!$F$5:$F$504,Pedidos!$E$5:$E$504,A20,Pedidos!$B$5:$B$504,">="&DATE($B$5,$B$4,1),Pedidos!$B$5:$B$504,"<"&DATE($B$5,$B$4+1,1),Pedidos!$M$5:$M$504,"<>Cancelado")) | C20: =IF(A20="","",SUMIFS(Pedidos!$I$5:$I$504,Pedidos!$E$5:$E$504,A20,Pedidos!$B$5:$B$504,">="&DATE($B$5,$B$4,1),Pedidos!$B$5:$B$504,"<"&DATE($B$5,$B$4+1,1),Pedidos!$M$5:$M$504,"<>Cancelado"))
A21: =IF('Catálogo'!A9="","",'Catálogo'!A9) | B21: =IF(A21="","",SUMIFS(Pedidos!$F$5:$F$504,Pedidos!$E$5:$E$504,A21,Pedidos!$B$5:$B$504,">="&DATE($B$5,$B$4,1),Pedidos!$B$5:$B$504,"<"&DATE($B$5,$B$4+1,1),Pedidos!$M$5:$M$504,"<>Cancelado")) | C21: =IF(A21="","",SUMIFS(Pedidos!$I$5:$I$504,Pedidos!$E$5:$E$504,A21,Pedidos!$B$5:$B$504,">="&DATE($B$5,$B$4,1),Pedidos!$B$5:$B$504,"<"&DATE($B$5,$B$4+1,1),Pedidos!$M$5:$M$504,"<>Cancelado"))
A22: =IF('Catálogo'!A10="","",'Catálogo'!A10) | B22: =IF(A22="","",SUMIFS(Pedidos!$F$5:$F$504,Pedidos!$E$5:$E$504,A22,Pedidos!$B$5:$B$504,">="&DATE($B$5,$B$4,1),Pedidos!$B$5:$B$504,"<"&DATE($B$5,$B$4+1,1),Pedidos!$M$5:$M$504,"<>Cancelado")) | C22: =IF(A22="","",SUMIFS(Pedidos!$I$5:$I$504,Pedidos!$E$5:$E$504,A22,Pedidos!$B$5:$B$504,">="&DATE($B$5,$B$4,1),Pedidos!$B$5:$B$504,"<"&DATE($B$5,$B$4+1,1),Pedidos!$M$5:$M$504,"<>Cancelado"))
A23: =IF('Catálogo'!A11="","",'Catálogo'!A11) | B23: =IF(A23="","",SUMIFS(Pedidos!$F$5:$F$504,Pedidos!$E$5:$E$504,A23,Pedidos!$B$5:$B$504,">="&DATE($B$5,$B$4,1),Pedidos!$B$5:$B$504,"<"&DATE($B$5,$B$4+1,1),Pedidos!$M$5:$M$504,"<>Cancelado")) | C23: =IF(A23="","",SUMIFS(Pedidos!$I$5:$I$504,Pedidos!$E$5:$E$504,A23,Pedidos!$B$5:$B$504,">="&DATE($B$5,$B$4,1),Pedidos!$B$5:$B$504,"<"&DATE($B$5,$B$4+1,1),Pedidos!$M$5:$M$504,"<>Cancelado"))
A24: =IF('Catálogo'!A12="","",'Catálogo'!A12) | B24: =IF(A24="","",SUMIFS(Pedidos!$F$5:$F$504,Pedidos!$E$5:$E$504,A24,Pedidos!$B$5:$B$504,">="&DATE($B$5,$B$4,1),Pedidos!$B$5:$B$504,"<"&DATE($B$5,$B$4+1,1),Pedidos!$M$5:$M$504,"<>Cancelado")) | C24: =IF(A24="","",SUMIFS(Pedidos!$I$5:$I$504,Pedidos!$E$5:$E$504,A24,Pedidos!$B$5:$B$504,">="&DATE($B$5,$B$4,1),Pedidos!$B$5:$B$504,"<"&DATE($B$5,$B$4+1,1),Pedidos!$M$5:$M$504,"<>Cancelado"))
A25: =IF('Catálogo'!A13="","",'Catálogo'!A13) | B25: =IF(A25="","",SUMIFS(Pedidos!$F$5:$F$504,Pedidos!$E$5:$E$504,A25,Pedidos!$B$5:$B$504,">="&DATE($B$5,$B$4,1),Pedidos!$B$5:$B$504,"<"&DATE($B$5,$B$4+1,1),Pedidos!$M$5:$M$504,"<>Cancelado")) | C25: =IF(A25="","",SUMIFS(Pedidos!$I$5:$I$504,Pedidos!$E$5:$E$504,A25,Pedidos!$B$5:$B$504,">="&DATE($B$5,$B$4,1),Pedidos!$B$5:$B$504,"<"&DATE($B$5,$B$4+1,1),Pedidos!$M$5:$M$504,"<>Cancelado"))
A26: =IF('Catálogo'!A14="","",'Catálogo'!A14) | B26: =IF(A26="","",SUMIFS(Pedidos!$F$5:$F$504,Pedidos!$E$5:$E$504,A26,Pedidos!$B$5:$B$504,">="&DATE($B$5,$B$4,1),Pedidos!$B$5:$B$504,"<"&DATE($B$5,$B$4+1,1),Pedidos!$M$5:$M$504,"<>Cancelado")) | C26: =IF(A26="","",SUMIFS(Pedidos!$I$5:$I$504,Pedidos!$E$5:$E$504,A26,Pedidos!$B$5:$B$504,">="&DATE($B$5,$B$4,1),Pedidos!$B$5:$B$504,"<"&DATE($B$5,$B$4+1,1),Pedidos!$M$5:$M$504,"<>Cancelado"))
A27: =IF('Catálogo'!A15="","",'Catálogo'!A15) | B27: =IF(A27="","",SUMIFS(Pedidos!$F$5:$F$504,Pedidos!$E$5:$E$504,A27,Pedidos!$B$5:$B$504,">="&DATE($B$5,$B$4,1),Pedidos!$B$5:$B$504,"<"&DATE($B$5,$B$4+1,1),Pedidos!$M$5:$M$504,"<>Cancelado")) | C27: =IF(A27="","",SUMIFS(Pedidos!$I$5:$I$504,Pedidos!$E$5:$E$504,A27,Pedidos!$B$5:$B$504,">="&DATE($B$5,$B$4,1),Pedidos!$B$5:$B$504,"<"&DATE($B$5,$B$4+1,1),Pedidos!$M$5:$M$504,"<>Cancelado"))
A28: =IF('Catálogo'!A16="","",'Catálogo'!A16) | B28: =IF(A28="","",SUMIFS(Pedidos!$F$5:$F$504,Pedidos!$E$5:$E$504,A28,Pedidos!$B$5:$B$504,">="&DATE($B$5,$B$4,1),Pedidos!$B$5:$B$504,"<"&DATE($B$5,$B$4+1,1),Pedidos!$M$5:$M$504,"<>Cancelado")) | C28: =IF(A28="","",SUMIFS(Pedidos!$I$5:$I$504,Pedidos!$E$5:$E$504,A28,Pedidos!$B$5:$B$504,">="&DATE($B$5,$B$4,1),Pedidos!$B$5:$B$504,"<"&DATE($B$5,$B$4+1,1),Pedidos!$M$5:$M$504,"<>Cancelado"))
... A46: =IF('Catálogo'!A34="","",'Catálogo'!A34) | B46: =IF(A46="","",SUMIFS(Pedidos!$F$5:$F$504,Pedidos!$E$5:$E$504,A46,Pedidos!$B$5:$B$504,">="&DATE($B$5,$B$4,1),Pedidos!$B$5:$B$504,"<"&DATE($B$5,$B$4+1,1),Pedidos!$M$5:$M$504,"<>Cancelado")) | C46: =IF(A46="","",SUMIFS(Pedidos!$I$5:$I$504,Pedidos!$E$5:$E$504,A46,Pedidos!$B$5:$B$504,">="&DATE($B$5,$B$4,1),Pedidos!$B$5:$B$504,"<"&DATE($B$5,$B$4+1,1),Pedidos!$M$5:$M$504,"<>Cancelado"))

Sheet Pedidos
A1: Pedidos
A2: Uma linha por produto do pedido. Mesmo Nº = mesmo pedido.
A4: Nº pedido | B4: Data do pedido | C4: Cliente | D4: Telefone | E4: Produto | F4: Qtd | G4: Preço unitário | H4: Desconto (R$) | I4: Total | J4: Entrega | K4: Pagamento | L4: Pago? | M4: Status | N4: Alerta
A5: 101 | B5: =TODAY()+(-6) | C5: Mariana Souza | D5: (11) 90000-0001 | E5: Bolo de pote | F5: 6 | G5: =IF(E5="","",IFERROR(VLOOKUP(E5,'Catálogo'!$A$5:$B$504,2,FALSE),0)) | H5: 0 | I5: =IF(E5="","",MAX(F5*G5-N(H5),0)) | J5: =TODAY()+(-4) | K5: Pix | L5: Sim | M5: Entregue | N5: =IF(OR(E5="",M5="Entregue",M5="Cancelado",J5=""),"",IF(J5<TODAY(),"ATRASADO",IF(J5=TODAY(),"ENTREGA HOJE","")))
A6: 102 | B6: =TODAY()+(-5) | C6: Carlos Lima | D6: (11) 90000-0002 | E6: Brigadeiro gourmet (cento) | F6: 2 | G6: =IF(E6="","",IFERROR(VLOOKUP(E6,'Catálogo'!$A$5:$B$504,2,FALSE),0)) | H6: 20 | I6: =IF(E6="","",MAX(F6*G6-N(H6),0)) | J6: =TODAY()+(-1) | K6: Cartão de crédito | L6: Sim | M6: Entregue | N6: =IF(OR(E6="",M6="Entregue",M6="Cancelado",J6=""),"",IF(J6<TODAY(),"ATRASADO",IF(J6=TODAY(),"ENTREGA HOJE","")))
A7: 102 | B7: =TODAY()+(-5) | C7: Carlos Lima | D7: (11) 90000-0002 | E7: Taxa de entrega | F7: 1 | G7: =IF(E7="","",IFERROR(VLOOKUP(E7,'Catálogo'!$A$5:$B$504,2,FALSE),0)) | H7: 0 | I7: =IF(E7="","",MAX(F7*G7-N(H7),0)) | J7: =TODAY()+(-1) | K7: Cartão de crédito | L7: Sim | M7: Entregue | N7: =IF(OR(E7="",M7="Entregue",M7="Cancelado",J7=""),"",IF(J7<TODAY(),"ATRASADO",IF(J7=TODAY(),"ENTREGA HOJE","")))
A8: 103 | B8: =TODAY()+(-3) | C8: Ana Paula | D8: (11) 90000-0003 | E8: Torta de limão inteira | F8: 1 | G8: =IF(E8="","",IFERROR(VLOOKUP(E8,'Catálogo'!$A$5:$B$504,2,FALSE),0)) | H8: 0 | I8: =IF(E8="","",MAX(F8*G8-N(H8),0)) | J8: =TODAY()+(-1) | K8: Pix | L8: Não | M8: Pronto | N8: =IF(OR(E8="",M8="Entregue",M8="Cancelado",J8=""),"",IF(J8<TODAY(),"ATRASADO",IF(J8=TODAY(),"ENTREGA HOJE","")))
A9: 104 | B9: =TODAY()+(-2) | C9: Buffet Alegria | D9: (11) 90000-0004 | E9: Kit festa 20 pessoas | F9: 2 | G9: =IF(E9="","",IFERROR(VLOOKUP(E9,'Catálogo'!$A$5:$B$504,2,FALSE),0)) | H9: 30 | I9: =IF(E9="","",MAX(F9*G9-N(H9),0)) | J9: =TODAY()+(0) | K9: Boleto | L9: Não | M9: Em produção | N9: =IF(OR(E9="",M9="Entregue",M9="Cancelado",J9=""),"",IF(J9<TODAY(),"ATRASADO",IF(J9=TODAY(),"ENTREGA HOJE","")))
A10: 105 | B10: =TODAY()+(-1) | C10: João Pedro | D10: (11) 90000-0005 | E10: Bolo de pote | F10: 10 | G10: =IF(E10="","",IFERROR(VLOOKUP(E10,'Catálogo'!$A$5:$B$504,2,FALSE),0)) | H10: 0 | I10: =IF(E10="","",MAX(F10*G10-N(H10),0)) | J10: =TODAY()+(2) | K10: Dinheiro | L10: Não | M10: Novo | N10: =IF(OR(E10="",M10="Entregue",M10="Cancelado",J10=""),"",IF(J10<TODAY(),"ATRASADO",IF(J10=TODAY(),"ENTREGA HOJE","")))
A11: 106 | B11: =TODAY()+(-1) | C11: Fernanda Reis | D11: (11) 90000-0006 | E11: Torta de limão inteira | F11: 1 | G11: =IF(E11="","",IFERROR(VLOOKUP(E11,'Catálogo'!$A$5:$B$504,2,FALSE),0)) | H11: 0 | I11: =IF(E11="","",MAX(F11*G11-N(H11),0)) | J11: =TODAY()+(3) | K11: Pix | L11: Sim | M11: Cancelado | N11: =IF(OR(E11="",M11="Entregue",M11="Cancelado",J11=""),"",IF(J11<TODAY(),"ATRASADO",IF(J11=TODAY(),"ENTREGA HOJE","")))
G12: =IF(E12="","",IFERROR(VLOOKUP(E12,'Catálogo'!$A$5:$B$504,2,FALSE),0)) | I12: =IF(E12="","",MAX(F12*G12-N(H12),0)) | N12: =IF(OR(E12="",M12="Entregue",M12="Cancelado",J12=""),"",IF(J12<TODAY(),"ATRASADO",IF(J12=TODAY(),"ENTREGA HOJE","")))
G13: =IF(E13="","",IFERROR(VLOOKUP(E13,'Catálogo'!$A$5:$B$504,2,FALSE),0)) | I13: =IF(E13="","",MAX(F13*G13-N(H13),0)) | N13: =IF(OR(E13="",M13="Entregue",M13="Cancelado",J13=""),"",IF(J13<TODAY(),"ATRASADO",IF(J13=TODAY(),"ENTREGA HOJE","")))
G14: =IF(E14="","",IFERROR(VLOOKUP(E14,'Catálogo'!$A$5:$B$504,2,FALSE),0)) | I14: =IF(E14="","",MAX(F14*G14-N(H14),0)) | N14: =IF(OR(E14="",M14="Entregue",M14="Cancelado",J14=""),"",IF(J14<TODAY(),"ATRASADO",IF(J14=TODAY(),"ENTREGA HOJE","")))
G15: =IF(E15="","",IFERROR(VLOOKUP(E15,'Catálogo'!$A$5:$B$504,2,FALSE),0)) | I15: =IF(E15="","",MAX(F15*G15-N(H15),0)) | N15: =IF(OR(E15="",M15="Entregue",M15="Cancelado",J15=""),"",IF(J15<TODAY(),"ATRASADO",IF(J15=TODAY(),"ENTREGA HOJE","")))
G16: =IF(E16="","",IFERROR(VLOOKUP(E16,'Catálogo'!$A$5:$B$504,2,FALSE),0)) | I16: =IF(E16="","",MAX(F16*G16-N(H16),0)) | N16: =IF(OR(E16="",M16="Entregue",M16="Cancelado",J16=""),"",IF(J16<TODAY(),"ATRASADO",IF(J16=TODAY(),"ENTREGA HOJE","")))
G17: =IF(E17="","",IFERROR(VLOOKUP(E17,'Catálogo'!$A$5:$B$504,2,FALSE),0)) | I17: =IF(E17="","",MAX(F17*G17-N(H17),0)) | N17: =IF(OR(E17="",M17="Entregue",M17="Cancelado",J17=""),"",IF(J17<TODAY(),"ATRASADO",IF(J17=TODAY(),"ENTREGA HOJE","")))
G18: =IF(E18="","",IFERROR(VLOOKUP(E18,'Catálogo'!$A$5:$B$504,2,FALSE),0)) | I18: =IF(E18="","",MAX(F18*G18-N(H18),0)) | N18: =IF(OR(E18="",M18="Entregue",M18="Cancelado",J18=""),"",IF(J18<TODAY(),"ATRASADO",IF(J18=TODAY(),"ENTREGA HOJE","")))
G19: =IF(E19="","",IFERROR(VLOOKUP(E19,'Catálogo'!$A$5:$B$504,2,FALSE),0)) | I19: =IF(E19="","",MAX(F19*G19-N(H19),0)) | N19: =IF(OR(E19="",M19="Entregue",M19="Cancelado",J19=""),"",IF(J19<TODAY(),"ATRASADO",IF(J19=TODAY(),"ENTREGA HOJE","")))
G20: =IF(E20="","",IFERROR(VLOOKUP(E20,'Catálogo'!$A$5:$B$504,2,FALSE),0)) | I20: =IF(E20="","",MAX(F20*G20-N(H20),0)) | N20: =IF(OR(E20="",M20="Entregue",M20="Cancelado",J20=""),"",IF(J20<TODAY(),"ATRASADO",IF(J20=TODAY(),"ENTREGA HOJE","")))
G21: =IF(E21="","",IFERROR(VLOOKUP(E21,'Catálogo'!$A$5:$B$504,2,FALSE),0)) | I21: =IF(E21="","",MAX(F21*G21-N(H21),0)) | N21: =IF(OR(E21="",M21="Entregue",M21="Cancelado",J21=""),"",IF(J21<TODAY(),"ATRASADO",IF(J21=TODAY(),"ENTREGA HOJE","")))
G22: =IF(E22="","",IFERROR(VLOOKUP(E22,'Catálogo'!$A$5:$B$504,2,FALSE),0)) | I22: =IF(E22="","",MAX(F22*G22-N(H22),0)) | N22: =IF(OR(E22="",M22="Entregue",M22="Cancelado",J22=""),"",IF(J22<TODAY(),"ATRASADO",IF(J22=TODAY(),"ENTREGA HOJE","")))
G23: =IF(E23="","",IFERROR(VLOOKUP(E23,'Catálogo'!$A$5:$B$504,2,FALSE),0)) | I23: =IF(E23="","",MAX(F23*G23-N(H23),0)) | N23: =IF(OR(E23="",M23="Entregue",M23="Cancelado",J23=""),"",IF(J23<TODAY(),"ATRASADO",IF(J23=TODAY(),"ENTREGA HOJE","")))
... G504: =IF(E504="","",IFERROR(VLOOKUP(E504,'Catálogo'!$A$5:$B$504,2,FALSE),0)) | I504: =IF(E504="","",MAX(F504*G504-N(H504),0)) | N504: =IF(OR(E504="",M504="Entregue",M504="Cancelado",J504=""),"",IF(J504<TODAY(),"ATRASADO",IF(J504=TODAY(),"ENTREGA HOJE","")))

Sheet Catálogo
A1: Catálogo
A2: Seus produtos ou serviços e o preço de venda.
A4: Produto / serviço | B4: Preço de venda | C4: Categoria
A5: Bolo de pote | B5: 12 | C5: Doces
A6: Brigadeiro gourmet (cento) | B6: 150 | C6: Doces
A7: Torta de limão inteira | B7: 85 | C7: Tortas
A8: Kit festa 20 pessoas | B8: 260 | C8: Kits
A9: Taxa de entrega | B9: 10 | C9: Serviços
